ciqreviews/__init__.py
ciqreviews/connectiq.py
ciqreviews/main.py
ciqreviews/test.py
ciqreviews-0.1.6.dist-info/METADATA
ciqreviews-0.1.6.dist-info/WHEEL
ciqreviews-0.1.6.dist-info/top_level.txt
ciqreviews-0.1.6.dist-info/RECORD
