Metadata-Version: 2.1
Name: ciqreviews
Version: 0.1.6
Summary: This package is used to analyse the downloads,reviews,ratings of some Garmin Connect IQ App
Home-page: https://github.com/Likenttt/connect-iq-spam-reviews
Author: li2niu
Author-email: <chuanyi.work@gmail.com>
License: UNKNOWN
Keywords: connectiq,garmin,ciq
Platform: UNKNOWN
Classifier: Development Status :: 3 - Alpha
Classifier: Intended Audience :: Developers
Classifier: Programming Language :: Python :: 3
Classifier: Operating System :: MacOS :: MacOS X
Classifier: Operating System :: Microsoft :: Windows
